unstructured2graph/__init__.py
unstructured2graph/loaders.py
unstructured2graph/memgraph.py
unstructured2graph-0.1.3.dist-info/METADATA
unstructured2graph-0.1.3.dist-info/WHEEL
unstructured2graph-0.1.3.dist-info/licenses/LICENSE
unstructured2graph-0.1.3.dist-info/RECORD
