Metadata-Version: 2.4
Name: unstructured2graph
Version: 0.1.3
Summary: Convert unstructured documents into knowledge graphs
Project-URL: Homepage, https://github.com/memgraph/ai-toolkit
Project-URL: Source, https://github.com/memgraph/ai-toolkit/tree/main/unstructured2graph
Project-URL: Issues, https://github.com/memgraph/ai-toolkit/issues
Author-email: Memgraph Tech Team <tech@memgraph.com>
License: MIT
License-File: LICENSE
Keywords: graph,integration,lightrag,memgraph,toolkit
Classifier: Intended Audience :: Developers
Classifier: License :: OSI Approved :: MIT License
Classifier: Programming Language :: Python :: 3
Classifier: Programming Language :: Python :: 3.10
Classifier: Programming Language :: Python :: 3.11
Classifier: Programming Language :: Python :: 3.12
Classifier: Programming Language :: Python :: 3.13
Requires-Python: >=3.10
Requires-Dist: lightrag-memgraph>=0.1.1
Requires-Dist: memgraph-toolbox>=0.1.8
Requires-Dist: unstructured>=0.12.6
Provides-Extra: all-docs
Requires-Dist: unstructured[all-docs]>=0.12.6; extra == 'all-docs'
Provides-Extra: test
Requires-Dist: pytest-asyncio>=0.21.0; extra == 'test'
Requires-Dist: pytest>=7.0.0; extra == 'test'
